present/__init__.py
present/__main__.py
present/__version__.py
present/cli.py
present/effects.py
present/markdown.py
present/slide.py
present/slideshow.py
present-0.6.0.dist-info/LICENSE
present-0.6.0.dist-info/METADATA
present-0.6.0.dist-info/WHEEL
present-0.6.0.dist-info/entry_points.txt
present-0.6.0.dist-info/top_level.txt
present-0.6.0.dist-info/RECORD
