Metadata-Version: 2.1
Name: present
Version: 0.6.0
Summary: A terminal-based presentation tool with colors and effects.
Home-page: https://github.com/vinayak-mehta/present
Author: Vinayak Mehta
Author-email: vmehta94@gmail.com
License: Apache 2.0
Project-URL: Documentation, https://present.readthedocs.io
Project-URL: Source, https://github.com/vinayak-mehta/present
Project-URL: Changelog, https://github.com/vinayak-mehta/present/blob/master/HISTORY.md
Platform: UNKNOWN
Classifier: Environment :: Console
Classifier: License :: OSI Approved :: Apache Software License
Classifier: Programming Language :: Python
Classifier: Programming Language :: Python :: 3.7
Classifier: Programming Language :: Python :: 3.8
Classifier: Programming Language :: Python :: 3.9
Classifier: Programming Language :: Python :: 3 :: Only
Requires-Python: >=3.7
Provides-Extra: dev
